watchtower/__init__.py
watchtower/py.typed
watchtower-3.3.1.dist-info/LICENSE
watchtower-3.3.1.dist-info/METADATA
watchtower-3.3.1.dist-info/WHEEL
watchtower-3.3.1.dist-info/top_level.txt
watchtower-3.3.1.dist-info/RECORD
