Metadata-Version: 2.1
Name: watchtower
Version: 3.3.1
Summary: Python CloudWatch Logging
Home-page: https://github.com/kislyuk/watchtower
Author: Andrey Kislyuk
Author-email: kislyuk@gmail.com
License: Apache Software License
Platform: MacOS X
Platform: Posix
Classifier: Intended Audience :: Developers
Classifier: License :: OSI Approved :: Apache Software License
Classifier: Operating System :: MacOS :: MacOS X
Classifier: Operating System :: POSIX
Classifier: Programming Language :: Python
Classifier: Programming Language :: Python :: 3
Classifier: Programming Language :: Python :: 3.8
Classifier: Programming Language :: Python :: 3.9
Classifier: Programming Language :: Python :: 3.10
Classifier: Programming Language :: Python :: 3.11
Classifier: Programming Language :: Python :: 3.12
Classifier: Programming Language :: Python :: Implementation :: CPython
Classifier: Programming Language :: Python :: Implementation :: PyPy
Classifier: Topic :: Software Development :: Libraries :: Python Modules
Requires-Python: >=3.8
License-File: LICENSE
Requires-Dist: boto3<2,>=1.9.253
Provides-Extra: tests
Requires-Dist: pyyaml; extra == "tests"
Requires-Dist: ruff; extra == "tests"
Requires-Dist: coverage; extra == "tests"
Requires-Dist: build; extra == "tests"
Requires-Dist: wheel; extra == "tests"
Requires-Dist: mypy; extra == "tests"
